<?xml version="1.0" encoding="utf-8"?>
<Elements xmlns="http://schemas.microsoft.com/sharepoint/">
  <Module Name="Scripts">
    <File Path="Scripts\App.js" Url="Scripts/App.js" ReplaceContent="TRUE" />
    <File Path="Scripts\knockout-3.4.0.js" Url="Scripts/knockout-3.4.0.js" ReplaceContent="TRUE" />
    <File Path="Scripts\jquery.fabric.js" Url="Scripts/jquery.fabric.js" ReplaceContent="TRUE" />
    <File Path="Scripts\jquery.fabric.min.js" Url="Scripts/jquery.fabric.min.js" ReplaceContent="TRUE" />
    <File Path="Scripts\jquery-2.2.3.min.map" Url="Scripts/jquery-2.2.3.min.map" ReplaceContent="TRUE" />
    <File Path="Scripts\jquery-2.2.3.min.js" Url="Scripts/jquery-2.2.3.min.js" ReplaceContent="TRUE" />
    <File Path="Scripts\jquery-2.2.3.js" Url="Scripts/jquery-2.2.3.js" ReplaceContent="TRUE" />
    <File Path="Scripts\jquery-2.2.3.intellisense.js" Url="Scripts/jquery-2.2.3.intellisense.js" ReplaceContent="TRUE" />
    <File Path="Scripts\angular.min.js.map" Url="Scripts/angular.min.js.map" ReplaceContent="TRUE" />
    <File Path="Scripts\angular.min.js" Url="Scripts/angular.min.js" ReplaceContent="TRUE" />
    <File Path="Scripts\angular.js" Url="Scripts/angular.js" ReplaceContent="TRUE" />
    <File Path="Scripts\angular-mocks.js" Url="Scripts/angular-mocks.js" ReplaceContent="TRUE" />
    <File Path="Scripts\ngOfficeUiFabric.min.js" Url="Scripts/ngOfficeUiFabric.min.js" ReplaceContent="TRUE" />
    <File Path="Scripts\ngOfficeUiFabric.js" Url="Scripts/ngOfficeUiFabric.js" ReplaceContent="TRUE" />
    <File Path="Scripts\ngApp.js" Url="Scripts/ngApp.js" ReplaceContent="TRUE" />
    <File Path="Scripts\testNGApp.js" Url="Scripts/testNGApp.js" ReplaceContent="TRUE" />
    <File Path="Scripts\AppNG.js" Url="Scripts/AppNG.js" ReplaceContent="TRUE" />
  </Module>
</Elements>